nasa_lsp/__init__.py
nasa_lsp/analyzer.py
nasa_lsp/cli.py
nasa_lsp/server.py
nasa_lsp-0.1.9.dist-info/METADATA
nasa_lsp-0.1.9.dist-info/WHEEL
nasa_lsp-0.1.9.dist-info/entry_points.txt
nasa_lsp-0.1.9.dist-info/top_level.txt
nasa_lsp-0.1.9.dist-info/RECORD
