Metadata-Version: 2.4
Name: nasa-lsp
Version: 0.1.9
Summary: A Language Server Protocol implementation that enforces NASA's Power of 10 rules for safety-critical code in Python.
Requires-Python: >=3.12
Requires-Dist: dead>=2.1.0
Requires-Dist: pygls>=2.0.0
Requires-Dist: typer>=0.21.1
Provides-Extra: dev
Requires-Dist: basedpyright>=1.29; extra == "dev"
Requires-Dist: bump-my-version>=0.31; extra == "dev"
Requires-Dist: hypothesis>=6.0.0; extra == "dev"
Requires-Dist: mutmut>=3.2; extra == "dev"
Requires-Dist: prek>=0.2.30; extra == "dev"
Requires-Dist: pytest-cov>=7.0.0; extra == "dev"
Requires-Dist: pytest>=8.0; extra == "dev"
Requires-Dist: ruff>=0.11; extra == "dev"
Requires-Dist: zensical>=0.0.17; extra == "dev"
Requires-Dist: dead>=2.1.0; extra == "dev"
